{
  "0": [
    {
      "Day": "4",
      "Month": "Dec",
      "title": "Panel + Networking",
      "postLink": "https://www.instagram.com/p/Cz35AcGNVxu/?hl=en",
      "imageLink": "https://utfs.io/f/91a3858d-23d1-45c5-93bb-b95e380bbcba-vxtlcy.jpg",
      "speakers": "Dartmouth team"
    },
    {
      "Day": "29",
      "Month": "Nov",
      "title": "Speaker Panel",
      "postLink": "https://www.instagram.com/p/CzEJClat9_t/?hl=en",
      "imageLink": "https://utfs.io/f/c1b45d4a-7176-412e-a3a9-ec067dc45452-icoupe.jpg",
      "speakers": "Lazard Panel"
    },
    {
      "Day": "28",
      "Month": "Nov",
      "title": "Senior Leadership",
      "postLink": "https://www.instagram.com/p/CzlUq6LtF_H/?hl=en",
      "imageLink": "https://utfs.io/f/039cb2a7-b0a9-42c8-9e92-bf0b1899de7c-8mvqc7.jpg",
      "speakers": "Stephane Etroy"
    },
    {
      "Day": "27",
      "Month": "Nov",
      "title": "Ice Skating",
      "postLink": "https://www.instagram.com/p/Cz_lPuPNWht/?hl=en",
      "imageLink": "https://utfs.io/f/61d008eb-0991-41c6-8bf1-29ad888e7824-tw8b8e.jpg",
      "speakers": null
    },
    {
      "Day": "20",
      "Month": "Nov",
      "title": "Speaker Event",
      "postLink": "https://www.instagram.com/p/Cyv4VNRtpmc/?hl=en",
      "imageLink": "https://utfs.io/f/9cce11b8-e883-4390-ba1b-730d6b635b96-cgtxh1.jpg",
      "speakers": "Juha Anjala"
    },
    {
      "Day": "17",
      "Month": "Nov",
      "title": "MBA Information Session",
      "postLink": "https://www.instagram.com/p/CzmHZRStaSn/?hl=en",
      "imageLink": "https://utfs.io/f/e145fbef-f1a9-48ac-aca1-bee3f005212b-do7y8b.jpg",
      "speakers": "Kellogg MBA Team"
    },
    {
      "Day": "16",
      "Month": "Nov",
      "title": "Speaker Event",
      "postLink": "https://instagram.com/p/CzJgdnCNNlK/?hl=en",
      "imageLink": "https://utfs.io/f/bf19ea02-021c-4a2a-9c6d-2120b996014f-h454ud.jpg",
      "speakers": "Hadleigh Beals"
    },
    {
      "Day": "26",
      "Month": "Oct",
      "title": "Finance Accelerator",
      "postLink": "https://www.instagram.com/p/CaHBLX-AR8f/?hl=en",
      "imageLink": "https://utfs.io/f/9b247c08-39ab-4f58-aea5-a01987308d03-cnmyck.jpg",
      "speakers": "AmplifyME"
    },
    {
      "Day": "20",
      "Month": "Oct",
      "title": "Spring Week Panel",
      "postLink": "https://www.instagram.com/p/CyI_JETtH9M/?hl=en",
      "imageLink": "https://utfs.io/f/06b3d9e9-2b34-4b2f-b0e3-099527800ee9-cxt5g9.jpg",
      "speakers": null
    },
    {
      "Day": "13",
      "Month": "Oct",
      "title": "Speaker Event",
      "postLink": "https://www.instagram.com/p/Cx-cm1kNGPP/?hl=en",
      "imageLink": "https://utfs.io/f/17073563-efde-415e-bf35-db5af02701e6-uup5h3.jpg",
      "speakers": "Imran Ansari"
    },
    {
      "Day": "6",
      "Month": "Oct",
      "title": "Evercore Panel Event",
      "postLink": "https://www.instagram.com/p/CxppIMzNzYh/?hl=en",
      "imageLink": "https://utfs.io/f/7791636f-b01f-4ce7-814b-aa84570acad2-4nhpdp.jpg",
      "speakers": null
    },
    {
      "Day": "2",
      "Month": "Oct",
      "title": "Speaker Event",
      "postLink": "https://www.instagram.com/p/CxBWBscNPZ1/?hl=en",
      "imageLink": "https://utfs.io/f/cc5f992d-62ce-43d4-906a-c1f7523bc9bd-qfemt3.jpg",
      "speakers": "Ken Griffin"
    }
  ],
  "1": [
    {
      "title": "",
      "speakers": "",
      "postLink": "",
      "imageLink": "",
      "Month": "",
      "Day": ""
    }
  ]
}
